source_railz/__init__.py
source_railz/components.py
source_railz/manifest.yaml
source_railz/run.py
source_railz/schemas/accounting_transactions.json
source_railz/schemas/accounts.json
source_railz/schemas/bank_accounts.json
source_railz/schemas/bank_transfers.json
source_railz/schemas/bills.json
source_railz/schemas/bills_credit_notes.json
source_railz/schemas/bills_payments.json
source_railz/schemas/businesses.json
source_railz/schemas/commerce_disputes.json
source_railz/schemas/commerce_orders.json
source_railz/schemas/commerce_products.json
source_railz/schemas/commerce_transactions.json
source_railz/schemas/connections.json
source_railz/schemas/customers.json
source_railz/schemas/deposits.json
source_railz/schemas/estimates.json
source_railz/schemas/inventory.json
source_railz/schemas/invoices.json
source_railz/schemas/invoices_credit_notes.json
source_railz/schemas/invoices_payments.json
source_railz/schemas/journal_entries.json
source_railz/schemas/purchase_orders.json
source_railz/schemas/refunds.json
source_railz/schemas/tax_rates.json
source_railz/schemas/tracking_categories.json
source_railz/schemas/vendors.json
source_railz/source.py
source_railz/spec.yaml
airbyte_source_railz-0.1.26.dist-info/METADATA
airbyte_source_railz-0.1.26.dist-info/WHEEL
airbyte_source_railz-0.1.26.dist-info/entry_points.txt
airbyte_source_railz-0.1.26.dist-info/RECORD
