Metadata-Version: 2.3
Name: airbyte-source-railz
Version: 0.1.26
Summary: Source implementation for Railz.
License: MIT
Author: Airbyte
Author-email: contact@airbyte.io
Requires-Python: >=3.9,<3.12
Classifier: License :: OSI Approved :: MIT License
Classifier: Programming Language :: Python :: 3
Classifier: Programming Language :: Python :: 3.9
Classifier: Programming Language :: Python :: 3.10
Classifier: Programming Language :: Python :: 3.11
Requires-Dist: airbyte-cdk (>=0,<1)
Requires-Dist: isodate (==0.6.1)
Requires-Dist: requests (==2.28.2)
Project-URL: Documentation, https://docs.airbyte.com/integrations/sources/railz
Project-URL: Homepage, https://airbyte.com
Project-URL: Repository, https://github.com/airbytehq/airbyte
